{
  "colors": {
    "backgroundColor": "#2c2f38",
    "boxColor": "#1cd61c",
    "fogColor": "#3d2c20",
    "buttonTextColor": "#ac9b9b",
    "buttonColor": "#a13636"
  },
  "@@editor": [
    {
      "key": "colors",
      "name": "Colors",
      "icon": "💅",
      "source": "colors.json",
      "fields": [
        {
          "key": "backgroundColor",
          "name": "Background color",
          "type": "color"
        },
        {
          "key": "fogColor",
          "name": "Fog color",
          "type": "color"
        },
        {
          "key": "buttonTextColor",
          "name": "Button Text color",
          "type": "color"
        },
        {
          "key": "buttonColor",
          "name": "Button color",
          "type": "color"
        }
      ]
    }
  ]
}