{
  "strings": {
    "emailInputEnabled": false,
    "fontFamily": "https://fonts.googleapis.com/css?family=Roboto Condensed",
    "title": "Leap",
    "instructions0": "Jump on the platforms and try not fall",
    "instructions1": "SPACEBAR = PC",
    "instructions2": "TAP = MOBILE",
    "instructions3": "SELECT PLAYER BELOW",
    "lives": "1",
    "playButtonText": "START",
    "scoreGain": "4",
    "minWorldSpeed": "25",
    "maxWorldSpeed": "100",
    "amount": "2",
    "duration": "12"
    
  },
  "@@editor": [
    {
      "key": "strings",
      "name": "Game Settings",
      "icon": "⚙️",
      "source": "strings.json",
      "fields": [
        {
          "key": "fontFamily",
          "name": "Game Font",
          "description": "Font family link from https://fonts.google.com/",
          "type": "text"
        },
        {
          "key": "title",
          "name": "Game Title",
          "description": "Name of your game",
          "type": "text"
        },
        {
          "key": "instructions0",
          "name": "Instructions0",
          "description": "Instructions0",
          "type": "text"
        },
        {
          "key": "instructions1",
          "name": "Instructions 1",
          "description": "Instructions Text 1",
          "type": "text"
        },
        {
          "key": "instructions2",
          "name": "Instructions 2",
          "description": "Instructions Text 2",
          "type": "text"
        },
        {
          "key": "instructions3",
          "name": "Instructions 3",
          "description": "Instructions Text 3",
          "type": "text"
        },
        {
          "key": "playButtonText",
          "name": "Play Button Text",
          "description": "Text",
          "type": "text"
        },
        {
          "key": "lives",
          "name": "Starting Lives",
          "description": "Starting Lives",
          "type": "text"
        },
        {
          "key": "scoreGain",
          "name": "Score Gain",
          "description": "Base score gain for each collectible",
          "type": "text"
        },
        {
          "key": "minWorldSpeed",
          "name": "Min World Speed",
          "description": "Minimum World Speed",
          "type": "text"
        },
        {
          "key": "maxWorldSpeed",
          "name": "Max World Speed",
          "description": "Maximum World Speed",
          "type": "text"
        },
        {
          "key": "duration",
          "name": "Duration of Speed increase",
          "description": "Duration by which World Speed increases",
          "type": "text"
        },
        {
          "key": "amount",
          "name": "Amount of Speed increase",
          "description": "Amount by which World Speed increases",
          "type": "text"
        }
      ]
    }
  ]
}